thinkthread/__init__.py
thinkthread/__main__.py
thinkthread/api.py
thinkthread/base_reasoner.py
thinkthread/cli.py
thinkthread/config.py
thinkthread/evaluation.py
thinkthread/llm/__init__.py
thinkthread/llm/anthropic_client.py
thinkthread/llm/base.py
thinkthread/llm/dummy.py
thinkthread/llm/hf_client.py
thinkthread/llm/openai_client.py
thinkthread/monitoring.py
thinkthread/prompting.py
thinkthread/prompts/__init__.py
thinkthread/prompts/alternative_prompt.j2
thinkthread/prompts/evaluate_prompt.j2
thinkthread/prompts/evaluation_prompt.j2
thinkthread/prompts/final_answer.j2
thinkthread/prompts/initial_prompt.j2
thinkthread/prompts/pairwise_prompt.j2
thinkthread/reasoning_utils.py
thinkthread/session.py
thinkthread/tree_thinker.py
thinkthread-0.8.1.dist-info/LICENSE
thinkthread-0.8.1.dist-info/METADATA
thinkthread-0.8.1.dist-info/WHEEL
thinkthread-0.8.1.dist-info/entry_points.txt
thinkthread-0.8.1.dist-info/RECORD
