Metadata-Version: 2.3
Name: thinkthread
Version: 0.8.1
Summary: Make your AI think before it speaks - advanced reasoning for LLMs
License: MIT
Author: Tomas Cupr
Author-email: work@tomcupr.com
Requires-Python: >=3.9,<4.0
Classifier: Intended Audience :: Developers
Classifier: License :: OSI Approved :: MIT License
Classifier: Programming Language :: Python :: 3
Classifier: Programming Language :: Python :: 3.9
Classifier: Programming Language :: Python :: 3.10
Classifier: Programming Language :: Python :: 3.11
Classifier: Programming Language :: Python :: 3.12
Classifier: Programming Language :: Python :: 3.13
Classifier: Topic :: Scientific/Engineering :: Artificial Intelligence
Requires-Dist: aiohttp (>=3.11.18,<4.0.0)
Requires-Dist: anthropic (>=0.8.0,<0.9.0)
Requires-Dist: jinja2 (>=3.1.6,<4.0.0)
Requires-Dist: openai (>=1.0.0,<2.0.0)
Requires-Dist: pydantic (>=2.5.0,<3.0.0)
Requires-Dist: requests (>=2.31.0,<3.0.0)
Requires-Dist: rich (>=14.0.0,<15.0.0)
Requires-Dist: typer (==0.9.0)
